oauthcli/__init__.py
oauthcli/clean.py
oauthcli/flow.py
oauthcli/providers.py
cli_oauth2-0.3.1.dist-info/LICENSE
cli_oauth2-0.3.1.dist-info/METADATA
cli_oauth2-0.3.1.dist-info/WHEEL
cli_oauth2-0.3.1.dist-info/entry_points.txt
cli_oauth2-0.3.1.dist-info/top_level.txt
cli_oauth2-0.3.1.dist-info/RECORD
