Metadata-Version: 2.1
Name: cli-oauth2
Version: 0.3.1
Summary: Helper library for OAuth2 in command-line tools
Author-email: Ilya Zverev <ilya@zverev.info>
License: 
Project-URL: Homepage, https://github.com/Zverik/cli-oauth2
Project-URL: Bug Tracker, https://github.com/Zverik/cli-oauth2/issues
Keywords: oauth,oauth2,cli,command line
Classifier: Programming Language :: Python :: 3
Classifier: Development Status :: 4 - Beta
Classifier: Intended Audience :: Developers
Classifier: License :: OSI Approved :: Apache Software License
Classifier: Operating System :: OS Independent
Classifier: Topic :: Software Development :: Libraries :: Python Modules
Requires-Python: >=3.9
License-File: LICENSE
Requires-Dist: requests-oauthlib
Requires-Dist: platformdirs
